{
  "unit": "m/s",
  "points": [
    {
      "time": "2026-07-22T22:00:00+00:00",
      "speed": 2.8,
      "gust": 5.1,
      "direction": 339
    },
    {
      "time": "2026-07-22T22:05:00+00:00",
      "speed": 1.6,
      "gust": 4.0,
      "direction": 331
    },
    {
      "time": "2026-07-22T22:10:00+00:00",
      "speed": 1.7,
      "gust": 3.6,
      "direction": 338
    },
    {
      "time": "2026-07-22T22:15:00+00:00",
      "speed": 1.4,
      "gust": 4.4,
      "direction": 351
    },
    {
      "time": "2026-07-22T22:20:00+00:00",
      "speed": 1.1,
      "gust": 4.4,
      "direction": 4
    },
    {
      "time": "2026-07-22T22:25:00+00:00",
      "speed": 1.0,
      "gust": 2.3,
      "direction": 293
    },
    {
      "time": "2026-07-22T22:30:00+00:00",
      "speed": 0.7,
      "gust": 2.3,
      "direction": 331
    }
  ]
}